MANIFEST.in
README
pyproject.toml
pyx_treap.c
pyx_treap.pyx
setup.py
pyx_treap.egg-info/PKG-INFO
pyx_treap.egg-info/SOURCES.txt
pyx_treap.egg-info/dependency_links.txt
pyx_treap.egg-info/requires.txt
pyx_treap.egg-info/top_level.txt