Metadata-Version: 2.1
Name: pyx-treap
Version: 2.0.20
Summary: Python implementation of treaps
Home-page: http://stromberg.dnsalias.org/~dstromberg/treap/
Author: Daniel Richard Stromberg
Author-email: strombrg@gmail.com
License: Apache v2
Platform: Cross platform
Classifier: Development Status :: 5 - Production/Stable
Classifier: Intended Audience :: Developers
Classifier: Programming Language :: Cython
Classifier: Programming Language :: Python :: 3
Classifier: Programming Language :: Python :: 2.7
